typelib/__init__.py
typelib/api.py
typelib/binding.py
typelib/codecs.py
typelib/constants.py
typelib/ctx.py
typelib/graph.py
typelib/py.typed
typelib/serdes.py
typelib/marshals/__init__.py
typelib/marshals/api.py
typelib/marshals/routines.py
typelib/py/__init__.py
typelib/py/classes.py
typelib/py/compat.py
typelib/py/contrib.py
typelib/py/frames.py
typelib/py/future.py
typelib/py/inspection.py
typelib/py/refs.py
typelib/unmarshals/__init__.py
typelib/unmarshals/api.py
typelib/unmarshals/routines.py
typelib-0.2.0.dist-info/METADATA
typelib-0.2.0.dist-info/WHEEL
typelib-0.2.0.dist-info/licenses/LICENSE
typelib-0.2.0.dist-info/RECORD
