Metadata-Version: 2.4
Name: typelib
Version: 0.2.0
Summary: A toolkit for marshalling, unmarshalling, and runtime validation leveraging type annotations.
Project-URL: Repository, https://github.com/seandstewart/typelib
Project-URL: Homepage, https://seandstewart.github.io/python-typelib/latest/
Author-email: Sean Stewart <sean.stewart@hey.com>
License-File: LICENSE
Keywords: annotations,data,serdes,typing,validation
Classifier: Development Status :: 3 - Alpha
Classifier: Intended Audience :: Developers
Classifier: License :: OSI Approved :: MIT License
Classifier: Natural Language :: English
Classifier: Operating System :: OS Independent
Classifier: Programming Language :: Python
Classifier: Programming Language :: Python :: 3 :: Only
Classifier: Programming Language :: Python :: 3.10
Classifier: Programming Language :: Python :: 3.11
Classifier: Programming Language :: Python :: 3.12
Classifier: Programming Language :: Python :: 3.13
Classifier: Programming Language :: Python :: Implementation :: CPython
Classifier: Topic :: Utilities
Classifier: Typing :: Typed
Requires-Python: <4.0,>=3.10
Requires-Dist: importlib-metadata<8,>=7.1.0; python_version < '3.10'
Requires-Dist: inflection~=0.5
Requires-Dist: more-itertools~=10.4
Requires-Dist: pendulum~=3.0
Requires-Dist: typing-extensions~=4.12
Provides-Extra: json
Requires-Dist: orjson~=3.4; extra == 'json'
